vtool_ibeis/__init__.py
vtool_ibeis/__main__.py
vtool_ibeis/_pyflann_backend.py
vtool_ibeis/_rhomb_dist.py
vtool_ibeis/blend.py
vtool_ibeis/chip.py
vtool_ibeis/clustering2.py
vtool_ibeis/confusion.py
vtool_ibeis/coverage_grid.py
vtool_ibeis/coverage_kpts.py
vtool_ibeis/demodata.py
vtool_ibeis/distance.py
vtool_ibeis/ellipse.py
vtool_ibeis/exif.py
vtool_ibeis/features.py
vtool_ibeis/fontdemo.py
vtool_ibeis/geometry.py
vtool_ibeis/histogram.py
vtool_ibeis/image.py
vtool_ibeis/image_filters.py
vtool_ibeis/image_shared.py
vtool_ibeis/inspect_matches.py
vtool_ibeis/keypoint.py
vtool_ibeis/linalg.py
vtool_ibeis/matching.py
vtool_ibeis/nearest_neighbors.py
vtool_ibeis/numpy_utils.py
vtool_ibeis/other.py
vtool_ibeis/patch.py
vtool_ibeis/quality_classifier.py
vtool_ibeis/score_normalization.py
vtool_ibeis/segmentation.py
vtool_ibeis/spatial_verification.py
vtool_ibeis/sver_c_wrapper.py
vtool_ibeis/symbolic.py
vtool_ibeis/trig.py
vtool_ibeis/util_math.py
vtool_ibeis-2.3.0.dist-info/LICENSE
vtool_ibeis-2.3.0.dist-info/METADATA
vtool_ibeis-2.3.0.dist-info/WHEEL
vtool_ibeis-2.3.0.dist-info/top_level.txt
vtool_ibeis-2.3.0.dist-info/RECORD
